resistors/__init__.py
resistors/errors.py
resistors/util.py
resistors-1.0.3.dist-info/LICENSE
resistors-1.0.3.dist-info/METADATA
resistors-1.0.3.dist-info/WHEEL
resistors-1.0.3.dist-info/top_level.txt
resistors-1.0.3.dist-info/RECORD
