Metadata-Version: 2.1
Name: resistors
Version: 1.0.3
Summary: Decode resistor color codes and encode resistance values
Home-page: https://github.com/gadhagod/resistors
Author: Aarav Borthakur
Author-email: gadhaguy13@gmail.com
License: UNKNOWN
Platform: UNKNOWN
Classifier: Programming Language :: Python :: 3
Classifier: License :: OSI Approved :: MIT License
Classifier: Operating System :: OS Independent
Requires-Python: >=3.6
